blockchain/__init__.py
blockchain/constants.py
blockchain/errors.py
blockchain/transaction.py
blockchain/utils.py
tests/__init__.py
tests/test_blockchain.py
transactiq-1.0.0.dist-info/licenses/LICENSE
transactiq-1.0.0.dist-info/METADATA
transactiq-1.0.0.dist-info/WHEEL
transactiq-1.0.0.dist-info/top_level.txt
transactiq-1.0.0.dist-info/RECORD
