Metadata-Version: 2.4
Name: Transactiq
Version: 1.0.0
Summary: A package for generating unsigned certificates with issuer and subject information.
Home-page: https://github.com/yourusername/Transactify
Author: Manil Jayswal
Author-email: EveryCRED <admin@everycred.com>
Project-URL: Homepage, https://github.com/pypa/sampleproject
Project-URL: Issues, https://github.com/pypa/sampleproject/issues
Classifier: Programming Language :: Python :: 3
Classifier: License :: OSI Approved :: MIT License
Classifier: Operating System :: OS Independent
Requires-Python: >=3.6
License-File: LICENSE
Dynamic: author
Dynamic: home-page
Dynamic: license-file
Dynamic: requires-python
